drfc_manager/__init__.py
drfc_manager/config/README.md
drfc_manager/config/__init__.py
drfc_manager/config/drfc-images/docker-compose-aws.yml
drfc_manager/config/drfc-images/docker-compose-cwlog.yml
drfc_manager/config/drfc-images/docker-compose-endpoint.yml
drfc_manager/config/drfc-images/docker-compose-eval-swarm.yml
drfc_manager/config/drfc-images/docker-compose-eval.yml
drfc_manager/config/drfc-images/docker-compose-keys.yml
drfc_manager/config/drfc-images/docker-compose-local-xorg-wsl.yml
drfc_manager/config/drfc-images/docker-compose-local-xorg.yml
drfc_manager/config/drfc-images/docker-compose-local.yml
drfc_manager/config/drfc-images/docker-compose-metrics.yml
drfc_manager/config/drfc-images/docker-compose-mount.yml
drfc_manager/config/drfc-images/docker-compose-robomaker-multi.yml
drfc_manager/config/drfc-images/docker-compose-robomaker-scripts.yml
drfc_manager/config/drfc-images/docker-compose-simapp.yml
drfc_manager/config/drfc-images/docker-compose-training-swarm.yml
drfc_manager/config/drfc-images/docker-compose-training.yml
drfc_manager/config/drfc-images/docker-compose-webviewer-swarm.yml
drfc_manager/config/drfc-images/docker-compose-webviewer.yml
drfc_manager/config/drfc-images/metrics/configuration.env
drfc_manager/config/drfc-images/metrics/grafana/provisioning/dashboards/dashboard.yml
drfc_manager/config/drfc-images/metrics/grafana/provisioning/dashboards/deepracer-training-template.json
drfc_manager/config/drfc-images/metrics/grafana/provisioning/datasources/influxdb.yml
drfc_manager/config/drfc-images/metrics/telegraf/etc/telegraf.conf
drfc_manager/config_env.py
drfc_manager/evaluation/get_compose_files.py
drfc_manager/evaluation/stop_evaluation_stack.py
drfc_manager/helpers/__init__.py
drfc_manager/helpers/files_manager.py
drfc_manager/helpers/training_params.py
drfc_manager/models/data_extraction.py
drfc_manager/models/env_operations.py
drfc_manager/models/model_operations.py
drfc_manager/models/storage_operations.py
drfc_manager-0.1.4.dist-info/LICENSE
drfc_manager-0.1.4.dist-info/METADATA
drfc_manager-0.1.4.dist-info/WHEEL
drfc_manager-0.1.4.dist-info/entry_points.txt
drfc_manager-0.1.4.dist-info/RECORD
