Metadata-Version: 2.3
Name: drfc-manager
Version: 0.1.4
Summary: A comprehensive Python package for managing AWS DeepRacer training workflows, model evaluation, and deployment. Features include pipeline management, custom model training, evaluation metrics, and visualization tools.
License: MIT
Author: João Victor Carvalho
Author-email: joaocarvoli@hotmail.com
Requires-Python: >=3.11,<4.0
Classifier: License :: OSI Approved :: MIT License
Classifier: Programming Language :: Python :: 3
Classifier: Programming Language :: Python :: 3.11
Classifier: Programming Language :: Python :: 3.12
Classifier: Programming Language :: Python :: 3.13
Requires-Dist: bump2version (==1.0.1)
Requires-Dist: docker (==7.1.0)
Requires-Dist: fastapi (>=0.115.12,<0.116.0)
Requires-Dist: gloe (==0.5.9)
Requires-Dist: jupyter (>=1.1.1,<2.0.0)
Requires-Dist: jupyterlab (>=4.3.6,<5.0.0)
Requires-Dist: minio (==7.2.7)
Requires-Dist: orjson (==3.10.3)
Requires-Dist: paramiko (==3.4.0)
Requires-Dist: pillow (>=11.2.1,<12.0.0)
Requires-Dist: pre-commit (>=4.2.0,<5.0.0)
Requires-Dist: pydantic-settings (>=2.0.0)
Requires-Dist: python-dotenv (==1.0.1)
Requires-Dist: python-on-whales (>=0.76.1,<0.77.0)
Requires-Dist: pyyaml (==6.0.1)
Requires-Dist: requests (==2.31)
Requires-Dist: ruff (>=0.11.11,<0.12.0)
Requires-Dist: streamlit (>=1.45.0,<2.0.0)
Requires-Dist: structlog (>=25.3.0,<26.0.0)
Requires-Dist: tqdm (>=4.67.1,<5.0.0)
Requires-Dist: uvicorn (>=0.34.2,<0.35.0)
